aliyunsdkpts/__init__.py
aliyunsdkpts/endpoint.py
aliyunsdkpts/request/__init__.py
aliyunsdkpts/request/v20201020/AdjustJMeterSceneSpeedRequest.py
aliyunsdkpts/request/v20201020/CreatePtsSceneBaseLineFromReportRequest.py
aliyunsdkpts/request/v20201020/CreatePtsSceneRequest.py
aliyunsdkpts/request/v20201020/DeletePtsSceneBaseLineRequest.py
aliyunsdkpts/request/v20201020/DeletePtsSceneRequest.py
aliyunsdkpts/request/v20201020/DeletePtsScenesRequest.py
aliyunsdkpts/request/v20201020/GetAllRegionsRequest.py
aliyunsdkpts/request/v20201020/GetJMeterLogsRequest.py
aliyunsdkpts/request/v20201020/GetJMeterSampleMetricsRequest.py
aliyunsdkpts/request/v20201020/GetJMeterSamplingLogsRequest.py
aliyunsdkpts/request/v20201020/GetJMeterSceneRunningDataRequest.py
aliyunsdkpts/request/v20201020/GetOpenJMeterSceneRequest.py
aliyunsdkpts/request/v20201020/GetPtsReportDetailsRequest.py
aliyunsdkpts/request/v20201020/GetPtsReportsBySceneIdRequest.py
aliyunsdkpts/request/v20201020/GetPtsSceneBaseLineRequest.py
aliyunsdkpts/request/v20201020/GetPtsSceneRequest.py
aliyunsdkpts/request/v20201020/GetPtsSceneRunningDataRequest.py
aliyunsdkpts/request/v20201020/GetPtsSceneRunningStatusRequest.py
aliyunsdkpts/request/v20201020/GetUserVpcSecurityGroupRequest.py
aliyunsdkpts/request/v20201020/GetUserVpcVSwitchRequest.py
aliyunsdkpts/request/v20201020/GetUserVpcsRequest.py
aliyunsdkpts/request/v20201020/ListEnvsRequest.py
aliyunsdkpts/request/v20201020/ListJMeterReportsRequest.py
aliyunsdkpts/request/v20201020/ListOpenJMeterScenesRequest.py
aliyunsdkpts/request/v20201020/ListPtsSceneRequest.py
aliyunsdkpts/request/v20201020/ModifyPtsSceneRequest.py
aliyunsdkpts/request/v20201020/RemoveEnvRequest.py
aliyunsdkpts/request/v20201020/RemoveOpenJMeterSceneRequest.py
aliyunsdkpts/request/v20201020/SaveEnvRequest.py
aliyunsdkpts/request/v20201020/SaveOpenJMeterSceneRequest.py
aliyunsdkpts/request/v20201020/SavePtsSceneRequest.py
aliyunsdkpts/request/v20201020/StartDebugPtsSceneRequest.py
aliyun_python_sdk_pts-1.0.0.dist-info/LICENSE
aliyun_python_sdk_pts-1.0.0.dist-info/METADATA
aliyun_python_sdk_pts-1.0.0.dist-info/WHEEL
aliyun_python_sdk_pts-1.0.0.dist-info/top_level.txt
aliyun_python_sdk_pts-1.0.0.dist-info/RECORD
